backup_tracker_micro/__init__.py
backup_tracker_micro/backup.py
backup_tracker_micro-0.1.9.dist-info/METADATA
backup_tracker_micro-0.1.9.dist-info/WHEEL
backup_tracker_micro-0.1.9.dist-info/licenses/LICENSE
backup_tracker_micro-0.1.9.dist-info/RECORD
