Metadata-Version: 2.3
Name: backup_tracker_micro
Version: 0.1.9
Summary: A rest client to transmit backup events
Author: Samuel Shiels
License-File: LICENSE
Classifier: License :: OSI Approved :: MIT License
Classifier: Operating System :: POSIX :: Linux
Classifier: Programming Language :: Python :: 3
Requires-Python: >=3.11.5
Requires-Dist: rest-client-micro>=0.3.18
